font2char2word2sent2doc/__init__.py
font2char2word2sent2doc/ar2word2sent2doc.py
font2char2word2sent2doc/char2word2sent2doc.py
font2char2word2sent2doc/char2word2sent2doc_test.py
font2char2word2sent2doc/font2char.py
font2char2word2sent2doc/font2char2word2sent2doc.py
font2char2word2sent2doc/font2char2word2sent2doc_test.py
font2char2word2sent2doc/font2char_test.py
font2char2word2sent2doc/rd2sent2doc.py
font2char2word2sent2doc/word2sent2doc.py
font2char2word2sent2doc/word2sent2doc_test.py
tensorflow_font2char2word2sent2doc-0.0.12.dist-info/DESCRIPTION.rst
tensorflow_font2char2word2sent2doc-0.0.12.dist-info/METADATA
tensorflow_font2char2word2sent2doc-0.0.12.dist-info/RECORD
tensorflow_font2char2word2sent2doc-0.0.12.dist-info/WHEEL
tensorflow_font2char2word2sent2doc-0.0.12.dist-info/metadata.json
tensorflow_font2char2word2sent2doc-0.0.12.dist-info/top_level.txt
