Metadata-Version: 2.0
Name: tensorflow-font2char2word2sent2doc
Version: 0.0.12
Summary: TensorFlow implementation of Hierarchical Attention Networks for Document Classification
Home-page: https://github.com/raviqqe/tensorflow-font2char2word2sent2doc/
Author: Yota Toyama
Author-email: raviqqe@gmail.com
License: Public Domain
Platform: UNKNOWN
Classifier: Development Status :: 3 - Alpha
Classifier: Intended Audience :: Developers
Classifier: License :: Public Domain
Classifier: Programming Language :: Python :: 3.6
Classifier: Topic :: Scientific/Engineering :: Artificial Intelligence
Classifier: Topic :: System :: Networking
Requires-Dist: argtyp
Requires-Dist: char2image
Requires-Dist: tensorflow-extenteten (<=1)
Requires-Dist: tensorflow-qnd (<=1)
Requires-Dist: tensorflow-qndex (<=1)
